dom_query/__init__.py
dom_query/compiler.py
dom_query/lexer.py
dom_query/minidom_api.py
dom_query/parser.py
dom_query/select.py
dom_query/symbols.py
dom_query/vm.py
dom_query-0.0.4.dist-info/LICENSE
dom_query-0.0.4.dist-info/METADATA
dom_query-0.0.4.dist-info/WHEEL
dom_query-0.0.4.dist-info/top_level.txt
dom_query-0.0.4.dist-info/RECORD
