Metadata-Version: 1.2
Name: dom-query
Version: 0.0.4
Summary: CSS selector syntax for python minidom and compatible DOM implementations
Home-page: https://gitlab.com/geusebi/dom_query
Author: Giampaolo Eusebi
Author-email: giampaolo.eusebi@gmail.com
License: GNU LGPL 3.0
Platform: UNKNOWN
Classifier: Development Status :: 4 - Beta
Classifier: Intended Audience :: Developers
Classifier: License :: OSI Approved
Classifier: License :: OSI Approved :: GNU Lesser General Public License v3 (LGPLv3)
Classifier: Operating System :: OS Independent
Classifier: Programming Language :: Python :: 3
Classifier: Programming Language :: Python :: 3.7
Classifier: Programming Language :: Python :: 3.6
Classifier: Topic :: Internet :: WWW/HTTP
Classifier: Topic :: Text Processing :: Markup
Classifier: Topic :: Text Processing :: Markup :: HTML
Requires-Python: >=3.6
